{"generatedAt":"2026-02-02T00:43:25.247Z","pipeline":{"status":"critical","lastSuccessful":"2026-02-02T00:43:25.248Z"},"datasets":{"events":{"recordCount":59,"lastUpdated":"2026-02-02T00:43:25.115Z","completeness":11.5,"issues":["83% missing pokemon","86% missing bonuses","85% missing raids","95% missing research","93% missing eggs"],"status":"critical"},"raids":{"recordCount":19,"lastUpdated":"2026-02-02T00:43:15.748Z","completeness":100,"issues":[],"status":"healthy"},"research":{"recordCount":60,"lastUpdated":"2026-02-02T00:43:18.772Z","completeness":100,"issues":[],"status":"healthy"},"eggs":{"recordCount":89,"lastUpdated":"2026-02-02T00:43:17.427Z","completeness":100,"issues":[],"status":"healthy"},"rocketLineups":{"recordCount":26,"lastUpdated":"2026-02-02T00:43:15.254Z","completeness":100,"issues":[],"status":"healthy"},"shinies":{"recordCount":1044,"lastUpdated":"2026-02-02T00:43:19.091Z","completeness":93,"issues":[],"status":"healthy"}},"summary":{"overallHealth":"critical","totalRecords":1297,"avgCompleteness":84.1,"criticalIssues":1,"warnings":0}}